ttsconvert.py
ttsconvert-0.1.dist-info/WHEEL
ttsconvert-0.1.dist-info/METADATA
ttsconvert-0.1.dist-info/RECORD
